evas_docs/__init__.py
evas_docs/build_docs.py
evas_docs/check_docs.py
evas_docs/conf_docs.py
evas_docs/deploy_docs.py
evas_docs/get_github_rev.py
evas_docs/sanitize_version.py
evas_docs/_static/DejaVuSans.ttf
evas_docs/_static/NotoSansSC-Regular.otf
evas_docs/_static/evas-logo.pdf
evas_docs/_static/evas-logo.svg
evas_docs/_static/theme_overrides.css
evas_docs/evas_extensions/__init__.py
evas_docs/evas_extensions/exclude_docs.py
evas_docs/evas_extensions/include_build_file.py
evas_docs/evas_extensions/latex_builder.py
evas_docs/evas_extensions/link_roles.py
evas_docs/evas_extensions/run_doxygen.py
evas_docs/evas_extensions/dummy_build_system/__init__.py
evas_docs/fonts/DejaVuSans.ttf
evas_docs/fonts/NotoSansSC-Regular.otf
evas_docs/generic_extensions/__init__.py
evas_docs/generic_extensions/add_warnings.py
evas_docs/generic_extensions/html_redirects.py
evas_docs/generic_extensions/list_filter.py
evas_docs/generic_extensions/toctree_filter.py
evas_docs/latex_templates/evas.sty
evas_docs/latex_templates/preamble.tex
evas_docs/latex_templates/titlepage.tex
evas_docs/util/__init__.py
evas_docs/util/util.py
evas_docs-0.0.4.dist-info/LICENSE
evas_docs-0.0.4.dist-info/METADATA
evas_docs-0.0.4.dist-info/WHEEL
evas_docs-0.0.4.dist-info/entry_points.txt
evas_docs-0.0.4.dist-info/top_level.txt
evas_docs-0.0.4.dist-info/RECORD
