Metadata-Version: 2.1
Name: evas-docs
Version: 0.0.4
Summary: Documentation building package used at EVAS Intelligence
Home-page: https://github.com/ikiwihome/evas-docs
Author: ikiwicc
Author-email: kiwi@ikiwi.cc
Project-URL: Bug Tracker, https://github.com/ikiwihome/evas-docs/issues
Classifier: Programming Language :: Python :: 3
Classifier: License :: OSI Approved :: MIT License
Classifier: Operating System :: OS Independent
Requires-Python: >=3.7
License-File: LICENSE
Requires-Dist: actdiag
Requires-Dist: alabaster
Requires-Dist: babel
Requires-Dist: blockdiag
Requires-Dist: breathe
Requires-Dist: cairocffi
Requires-Dist: cairosvg
Requires-Dist: certifi
Requires-Dist: cffi
Requires-Dist: charset-normalizer
Requires-Dist: colorama
Requires-Dist: commonmark
Requires-Dist: cssselect2
Requires-Dist: defusedxml
Requires-Dist: docutils
Requires-Dist: funcparserlib
Requires-Dist: idna
Requires-Dist: imagesize
Requires-Dist: jinja2
Requires-Dist: markupSafe
Requires-Dist: nwdiag
Requires-Dist: packaging
Requires-Dist: pillow ==9.5.0
Requires-Dist: pycparser
Requires-Dist: pygments
Requires-Dist: pyYAML
Requires-Dist: recommonmark
Requires-Dist: requests
Requires-Dist: seqdiag
Requires-Dist: six
Requires-Dist: snowballstemmer
Requires-Dist: sphinx
Requires-Dist: sphinx-copybutton
Requires-Dist: sphinx-notfound-page
Requires-Dist: sphinx-rtd-theme
Requires-Dist: sphinx-selective-exclude
Requires-Dist: sphinxcontrib-actdiag
Requires-Dist: sphinxcontrib-applehelp
Requires-Dist: sphinxcontrib-blockdiag
Requires-Dist: sphinxcontrib-devhelp
Requires-Dist: sphinxcontrib-htmlhelp
Requires-Dist: sphinxcontrib-jquery
Requires-Dist: sphinxcontrib-jsmath
Requires-Dist: sphinxcontrib-nwdiag
Requires-Dist: sphinxcontrib-qthelp
Requires-Dist: sphinxcontrib-seqdiag
Requires-Dist: sphinxcontrib-serializinghtml
Requires-Dist: sphinxcontrib-svg2pdfconverter
Requires-Dist: svgwrite
Requires-Dist: tinycss2
Requires-Dist: urllib3
Requires-Dist: webcolors
Requires-Dist: webencodings
